sphinxcontrib/youtube/__init__.py
sphinxcontrib/youtube/peertube.py
sphinxcontrib/youtube/utils.py
sphinxcontrib/youtube/vimeo.py
sphinxcontrib/youtube/youtube.py
sphinxcontrib_youtube-1.4.0.dist-info/WHEEL
sphinxcontrib_youtube-1.4.0.dist-info/METADATA
sphinxcontrib_youtube-1.4.0.dist-info/RECORD
